dslb/__init__.py
dslb/__main__.py
dslb/rsyncy_modded.py
dslb-1.0.1.dist-info/LICENSE
dslb-1.0.1.dist-info/METADATA
dslb-1.0.1.dist-info/WHEEL
dslb-1.0.1.dist-info/top_level.txt
dslb-1.0.1.dist-info/RECORD
