Metadata-Version: 2.1
Name: dslb
Version: 1.0.1
Summary: A rsync wrapper that makes the Linux full system backups and restores easier than ever.
Home-page: https://github.com/RemiZlatinis/DSLB
Author: Apostolos Zlatinis
Author-email: remizlatinis@gmail.com
License: UNKNOWN
Project-URL: Bug Tracker, https://github.com/RemiZlatinis/DSLB/issues
Platform: UNKNOWN
Classifier: Programming Language :: Python :: 3
Classifier: License :: OSI Approved :: GNU General Public License v2 (GPLv2)
Classifier: Operating System :: POSIX :: Linux
Requires-Python: >=3.6
License-File: LICENSE
